{
    "name": "Benin Bronze Plaques",
    "domain": "cultural_artifact",
    "entity_type": "metal plaques and sculptures",
    "alternative_names": [
        "Ama"
    ],
    "primary_sources": [
        "Wikipedia",
        "British Museum records",
        "Dan Hicks' scholarly works"
    ],
    "visual_attributes": {
        "morphology": "rectangular plaques with relief images",
        "distinctive_features": [
            "depictions of historical scenes and themes",
            "intricate relief work",
            "use of lost-wax casting technique"
        ],
        "color_palette": [
            "bronze",
            "brass",
            "patina green"
        ],
        "texture": "smooth with raised relief patterns",
        "size_and_scale": "varies, typically medium-sized plaques",
        "structural_arrangement": "hung on palace pillars with nails",
        "domain_specific_visual": {
            "material_composition": "primarily brass, some bronze",
            "decorative_elements": "historical and ceremonial motifs"
        }
    },
    "functional_attributes": {
        "primary_function": "decoration of the royal palace",
        "secondary_functions": [
            "glorification of the Oba",
            "historical documentation"
        ],
        "domain_specific_functional": {
            "ceremonial_role": "used in courtly rituals",
            "symbolic_role": "representation of divine kingship"
        }
    },
    "relational_attributes": {
        "relationships": [
            {
                "type": "CREATED_BY",
                "target": "Guild of Benin Bronze Casters",
                "description": "The guild responsible for crafting the plaques."
            },
            {
                "type": "ASSOCIATED_WITH",
                "target": "Kingdom of Benin",
                "description": "The cultural and historical context of the plaques."
            },
            {
                "type": "INFLUENCED_BY",
                "target": "Kingdom of Ife",
                "description": "Possible influence on Benin's bronze metalworking techniques."
            }
        ],
        "associated_entities": [
            "Oba of Benin",
            "Iyoba of Benin"
        ],
        "symbolic_items": [
            "manillas",
            "ivory carvings"
        ]
    },
    "contextual_attributes": {
        "origin": "Kingdom of Benin, present-day Edo State, Nigeria",
        "historical_period": "14th to 19th centuries",
        "geographic_range": "Southern Nigeria",
        "cultural_significance": "Represents the artistic and cultural achievements of the Edo people",
        "primary_sources": [
            "Wikipedia",
            "British Museum records"
        ]
    },
    "contrastive_constraints": [
        "NOT generic bronze sculptures",
        "NOT modern or contemporary art styles",
        "NOT unrelated to African cultural heritage"
    ]
}